NectaPy/__init__.py
NectaPy/main.py
NectaPy/pre.py
NectaPy/supportingYear.txt
NectaPy/t.py
NectaPy-0.11.0.dist-info/METADATA
NectaPy-0.11.0.dist-info/WHEEL
NectaPy-0.11.0.dist-info/top_level.txt
NectaPy-0.11.0.dist-info/RECORD
