Metadata-Version: 2.2
Name: NectaPy
Version: 0.11.0
Summary: A Python package for accessing NECTA (National Examinations Council of Tanzania) results
Home-page: https://github.com/Henryle-hd/NectaPy
Author: Henrylee
Author-email: henrydionizi@gmail.com
Classifier: Programming Language :: Python :: 3
Classifier: License :: OSI Approved :: MIT License
Classifier: Operating System :: OS Independent
Requires-Python: >=3.6
Requires-Dist: beautifulsoup4>=4.12.3
Requires-Dist: requests>=2.25.1
Dynamic: author
Dynamic: author-email
Dynamic: classifier
Dynamic: description
Dynamic: description-content-type
Dynamic: home-page
Dynamic: requires-dist
Dynamic: requires-python
Dynamic: summary
